postgres_schema_ensurer/__init__.py
postgres_schema_ensurer/postgres.py
postgres_schema_ensurer-0.2.0.dist-info/METADATA
postgres_schema_ensurer-0.2.0.dist-info/WHEEL
postgres_schema_ensurer-0.2.0.dist-info/RECORD
